sdk/block.py
sdk/block_bookmark.py
sdk/block_breadcrumb.py
sdk/block_bulleted_list_item.py
sdk/block_callout.py
sdk/block_child_database.py
sdk/block_child_page.py
sdk/block_code.py
sdk/block_divider.py
sdk/block_embed.py
sdk/block_equation.py
sdk/block_file.py
sdk/block_heading_1.py
sdk/block_heading_2.py
sdk/block_heading_3.py
sdk/block_image.py
sdk/block_link_preview.py
sdk/block_numbered_list_item.py
sdk/block_paragraph.py
sdk/block_parent_id.py
sdk/block_pdf.py
sdk/block_quote.py
sdk/bookmark.py
sdk/bulleted_list_item.py
sdk/callout.py
sdk/child_database.py
sdk/child_page.py
sdk/client.py
sdk/code.py
sdk/comment.py
sdk/database.py
sdk/database_annotations.py
sdk/database_cover.py
sdk/database_icon.py
sdk/database_parent_id.py
sdk/database_tag.py
sdk/database_text.py
sdk/database_title.py
sdk/embed.py
sdk/emoji_icon.py
sdk/equation.py
sdk/error.py
sdk/error_exception.py
sdk/external_icon.py
sdk/external_object.py
sdk/file.py
sdk/file_icon.py
sdk/file_object.py
sdk/heading.py
sdk/icon.py
sdk/link.py
sdk/link_preview.py
sdk/numbered_list_item.py
sdk/page.py
sdk/page_parent_id.py
sdk/page_tag.py
sdk/paragraph.py
sdk/parent_id.py
sdk/pdf.py
sdk/pdf_external.py
sdk/pdf_file.py
sdk/person.py
sdk/quote.py
sdk/rich_text.py
sdk/rich_text_annotation.py
sdk/rich_text_equation.py
sdk/rich_text_text.py
sdk/text.py
sdk/user.py
sdk/user_collection.py
sdk/user_tag.py
sdk/workspace_parent_id.py
sdkfabric_notion-0.2.0.dist-info/LICENSE
sdkfabric_notion-0.2.0.dist-info/METADATA
sdkfabric_notion-0.2.0.dist-info/WHEEL
sdkfabric_notion-0.2.0.dist-info/top_level.txt
sdkfabric_notion-0.2.0.dist-info/RECORD
